pollutants_annotations-0.1.1.dist-info/licenses/LICENSE
pollutants_model_dataset/__init__.py
pollutants_annotations-0.1.1.dist-info/METADATA
pollutants_annotations-0.1.1.dist-info/WHEEL
pollutants_annotations-0.1.1.dist-info/top_level.txt
pollutants_annotations-0.1.1.dist-info/RECORD
