Metadata-Version: 2.4
Name: pollutants-annotations
Version: 0.1.1
Summary: 污染物识别神经网络的训练数据集
Home-page: https://github.com/renarddsfsdfdsfefadfsdfd/Brianzhang-ARTI
Author: Yaolin Zhang
Author-email: zhangyaolin@stu2022.jnu.edu.cn
Project-URL: Bug Tracker, https://github.com/yourusername/pollutants-annotations/issues
Classifier: Programming Language :: Python :: 3
Classifier: License :: OSI Approved :: MIT License
Classifier: Operating System :: OS Independent
Requires-Python: >=3.7
License-File: LICENSE
Requires-Dist: pandas>=1.3.0
Dynamic: license-file
